{
   "author":"Cicero",
   "publisher":"publisher_id",
   "build":[
      {
         "resources":{
            "gold":0,
            "food":6,
            "stone":0,
            "build":0,
            "wood":0
         },
         "buildings":[
            {
               "type":"house",
               "count":2
            }
         ],
         "type":"newVillagers",
         "count":6,
         "task":"sheep"
      },
      {
         "count":4,
         "type":"newVillagers",
         "resources":{
            "wood":4,
            "build":0,
            "stone":0,
            "gold":0,
            "food":6
         },
         "task":"wood"
      },
      {
         "resources":{
            "stone":0,
            "build":0,
            "wood":4,
            "food":8,
            "gold":0
         },
         "type":"newVillagers",
         "count":2,
         "task":"boar"
      },
      {
         "resources":{
            "wood":4,
            "stone":0,
            "build":0,
            "food":12,
            "gold":0
         },
         "count":4,
         "task":"berries",
         "type":"newVillagers",
         "buildings":[
            {
               "count":2,
               "type":"house"
            },
            {
               "type":"mill",
               "count":1
            }
         ]
      },
      {
         "type":"boar",
         "task":"boar",
         "count":0,
         "resources":{
            "wood":4,
            "stone":0,
            "gold":0,
            "build":0,
            "food":12
         }
      },
      {
         "resources":{
            "gold":0,
            "food":12,
            "wood":9,
            "stone":0,
            "build":0
         },
         "task":"wood",
         "type":"newVillagers",
         "count":5
      },
      {
         "task":"sheep",
         "count":2,
         "type":"newVillagers",
         "resources":{
            "build":0,
            "stone":0,
            "wood":9,
            "food":14,
            "gold":0
         }
      },
      {
         "type":"moveVillagers",
         "count":10,
         "to":"farms",
         "resources":{
            "gold":0,
            "wood":9,
            "food":14,
            "build":0,
            "stone":0
         },
         "from":"sheep"
      },
      {
         "task":"gold",
         "count":4,
         "type":"newVillagers",
         "resources":{
            "build":0,
            "stone":0,
            "wood":9,
            "food":14,
            "gold":4
         }
      },
      {
         "type":"research",
         "resources":{
            "food":14,
            "build":0,
            "stone":0,
            "wood":9,
            "gold":4
         },
         "tech":[
            "loom"
         ]
      },
      {
         "type":"ageUp",
         "age":"feudalAge",
         "resources":{
            "build":0,
            "gold":4,
            "stone":0,
            "food":14,
            "wood":9
         }
      },
      {
         "resources":{
            "wood":9,
            "stone":0,
            "build":0,
            "food":14,
            "gold":6
         },
         "count":2,
         "task":"gold",
         "type":"newVillagers",
         "buildings":[
            {
               "count":1,
               "type":"market"
            },
            {
               "type":"blacksmith",
               "count":1
            }
         ]
      },
      {
         "tech":[
            "doubleBitAxe"
         ],
         "resources":{
            "wood":9,
            "stone":0,
            "build":0,
            "food":14,
            "gold":6
         },
         "type":"research"
      },
      {
         "resources":{
            "wood":9,
            "stone":0,
            "build":0,
            "food":14,
            "gold":6
         },
         "type":"newAge",
         "age":"castleAge"
      },
      {
         "count":2,
         "type":"newVillagers",
         "resources":{
            "wood":9,
            "food":14,
            "stone":0,
            "gold":8,
            "build":0
         },
         "buildings":[
            {
               "count":1,
               "type":"monastery"
            },
            {
               "count":1,
               "type":"siegeWorkshop"
            }
         ],
         "task":"gold"
      },
      {
         "age":"imperialAge",
         "type":"ageUp",
         "resources":{
            "gold":8,
            "build":0,
            "food":14,
            "stone":0,
            "wood":9
         }
      }
   ],
   "pop":{
      "imperialAge":32,
      "castleAge":30,
      "feudalAge":28
   },
   "id":37,
   "image":"Archer",
   "reference":"",
   "civilization":"Generic",
   "imageURL":"https://firebasestorage.googleapis.com/v0/b/build-order-guide.appspot.com/o/Images%2FArcher.png?alt=media&token=049d898a-7322-4520-8597-da91446238e7",
   "description":"Arena build. Byzantines are one of the best civs for a fast Imperial due to the reduced cost, and they have strong options including monks and gunpowder.",
   "status":"published",
   "title":"Fast Imperial",
   "uptime":{
      "feudalAge":"10:05",
      "castleAge":"19:00",
      "imperialAge":"19:40"
   },
   "difficulty":1,
   "attributes":[
      "fastFeudal"
   ]
}
